{
  "scenario": "drag-selection-sweep",
  "label": "baseline",
  "samples": 3,
  "aggregate": {
    "inp": 24,
    "interactions": 17,
    "longTasks": {
      "count": 0,
      "sum": 0,
      "max": 0
    },
    "longAnimationFrames": {
      "count": 0,
      "sum": 0,
      "max": 0,
      "maxBlocking": 0
    },
    "frames": {
      "count": 225,
      "mean": 16.666,
      "stddev": 0.058,
      "median": 16.7,
      "p95": 16.7,
      "max": 16.8
    }
  },
  "perSample": [
    {
      "inp": 40,
      "interactions": 17,
      "longTasks": {
        "count": 0,
        "sum": 0,
        "max": 0
      },
      "longAnimationFrames": {
        "count": 0,
        "sum": 0,
        "max": 0,
        "maxBlocking": 0
      },
      "frames": {
        "count": 235,
        "mean": 16.666,
        "stddev": 0.056,
        "median": 16.7,
        "p95": 16.7,
        "max": 16.8
      }
    },
    {
      "inp": 24,
      "interactions": 17,
      "longTasks": {
        "count": 0,
        "sum": 0,
        "max": 0
      },
      "longAnimationFrames": {
        "count": 0,
        "sum": 0,
        "max": 0,
        "maxBlocking": 0
      },
      "frames": {
        "count": 222,
        "mean": 16.666,
        "stddev": 0.058,
        "median": 16.7,
        "p95": 16.7,
        "max": 16.8
      }
    },
    {
      "inp": 24,
      "interactions": 15,
      "longTasks": {
        "count": 0,
        "sum": 0,
        "max": 0
      },
      "longAnimationFrames": {
        "count": 0,
        "sum": 0,
        "max": 0,
        "maxBlocking": 0
      },
      "frames": {
        "count": 225,
        "mean": 16.666,
        "stddev": 0.063,
        "median": 16.7,
        "p95": 16.8,
        "max": 16.8
      }
    }
  ],
  "baseline": {
    "inp": 24,
    "interactions": 15,
    "longTasks": {
      "count": 0,
      "sum": 0,
      "max": 0
    },
    "longAnimationFrames": {
      "count": 0,
      "sum": 0,
      "max": 0,
      "maxBlocking": 0
    },
    "frames": {
      "count": 224,
      "median": 16.7,
      "p95": 16.7,
      "max": 16.8
    }
  },
  "recordedAt": "2026-05-23T00:16:54.316Z"
}
