{
  "scenario": "shift-multi-select-burst",
  "label": "baseline",
  "samples": 3,
  "aggregate": {
    "inp": 24,
    "interactions": 9,
    "longTasks": {
      "count": 0,
      "sum": 0,
      "max": 0
    },
    "longAnimationFrames": {
      "count": 0,
      "sum": 0,
      "max": 0,
      "maxBlocking": 0
    },
    "frames": {
      "count": 25,
      "mean": 16.667,
      "stddev": 0.047,
      "median": 16.7,
      "p95": 16.7,
      "max": 16.7
    }
  },
  "perSample": [
    {
      "inp": 40,
      "interactions": 9,
      "longTasks": {
        "count": 0,
        "sum": 0,
        "max": 0
      },
      "longAnimationFrames": {
        "count": 0,
        "sum": 0,
        "max": 0,
        "maxBlocking": 0
      },
      "frames": {
        "count": 33,
        "mean": 16.667,
        "stddev": 0.047,
        "median": 16.7,
        "p95": 16.7,
        "max": 16.7
      }
    },
    {
      "inp": 24,
      "interactions": 9,
      "longTasks": {
        "count": 0,
        "sum": 0,
        "max": 0
      },
      "longAnimationFrames": {
        "count": 0,
        "sum": 0,
        "max": 0,
        "maxBlocking": 0
      },
      "frames": {
        "count": 25,
        "mean": 16.668,
        "stddev": 0.047,
        "median": 16.7,
        "p95": 16.7,
        "max": 16.7
      }
    },
    {
      "inp": 24,
      "interactions": 9,
      "longTasks": {
        "count": 0,
        "sum": 0,
        "max": 0
      },
      "longAnimationFrames": {
        "count": 0,
        "sum": 0,
        "max": 0,
        "maxBlocking": 0
      },
      "frames": {
        "count": 25,
        "mean": 16.664,
        "stddev": 0.048,
        "median": 16.7,
        "p95": 16.7,
        "max": 16.7
      }
    }
  ],
  "baseline": {
    "inp": 24,
    "interactions": 9,
    "longTasks": {
      "count": 0,
      "sum": 0,
      "max": 0
    },
    "longAnimationFrames": {
      "count": 0,
      "sum": 0,
      "max": 0,
      "maxBlocking": 0
    },
    "frames": {
      "count": 25,
      "median": 16.7,
      "p95": 16.8,
      "max": 16.8
    }
  },
  "recordedAt": "2026-05-23T00:16:42.484Z"
}
